easy_fossy/__init__.py
easy_fossy/models.py
easy_fossy-2.4.13.dist-info/entry_points.txt
easy_fossy-2.4.13.dist-info/LICENSE
easy_fossy-2.4.13.dist-info/METADATA
easy_fossy-2.4.13.dist-info/WHEEL
easy_fossy-2.4.13.dist-info/RECORD
