Metadata-Version: 2.1
Name: easy_fossy
Version: 2.4.13
Summary: fossology API wrapper in python 3.10
License: MIT
Author: dinesh_ravi
Requires-Python: >=3.9,<4.0
Classifier: License :: OSI Approved :: MIT License
Classifier: Programming Language :: Python :: 3
Classifier: Programming Language :: Python :: 3.9
Classifier: Programming Language :: Python :: 3.10
Classifier: Programming Language :: Python :: 3.11
Classifier: Programming Language :: Python :: 3.12
Requires-Dist: certifi (>=2023.5.7,<2024.0.0)
Requires-Dist: charset-normalizer (>=2.0.7,<3.0.0)
Requires-Dist: idna (>=3.3,<4.0)
Requires-Dist: pydantic (>=2.7.2,<3.0.0)
Requires-Dist: requests (>=2.26.0,<3.0.0)
Requires-Dist: requests-toolbelt (>=1.0.0,<2.0.0)
Requires-Dist: typing-extensions (>=4.7.0,<5.0.0)
Requires-Dist: urllib3 (>=1.26.7,<2.0.0)
